DataNormalizer/__init__.py
DataNormalizer/normalise.py
DataNormalizer/validate.py
DataNormalizer-1.3.4.dist-info/LICENSE
DataNormalizer-1.3.4.dist-info/METADATA
DataNormalizer-1.3.4.dist-info/WHEEL
DataNormalizer-1.3.4.dist-info/top_level.txt
DataNormalizer-1.3.4.dist-info/RECORD
