Metadata-Version: 2.1
Name: DataNormalizer
Version: 1.3.4
Summary: Package to help with normalizing data needed for the platform!
Author: Realstats
Author-email: info@realstats.com
License: MIT
Keywords: data DataNormalizer
License-File: LICENSE
Requires-Dist: numpy
Requires-Dist: pandas
Requires-Dist: mock
Requires-Dist: openpyxl
